setup.cfg
setup.py
graphql_to_rest/__init__.py
graphql_to_rest/types.py
graphql_to_rest.egg-info/PKG-INFO
graphql_to_rest.egg-info/SOURCES.txt
graphql_to_rest.egg-info/dependency_links.txt
graphql_to_rest.egg-info/requires.txt
graphql_to_rest.egg-info/top_level.txt
tests/__init__.py
tests/app.py
tests/compressed_schema.py
tests/conftest.py
tests/expressive_schema.py
tests/test_externalrestfield.py