Metadata-Version: 1.0
Name: graphql-to-rest
Version: 1.0
Summary: Make any REST API compatible with GraphQL
Home-page: https://github.com/curiousest/graphql-to-rest
Author: Douglas Hindson
Author-email: dmhindson+pypi@gmail.com
License: UNKNOWN
Platform: UNKNOWN
